{
    "head_message": {
		"heading": "We’ll Create & Improve The Performance of All Your Content",
		"text_line": "We create engaging content for multiple platforms so you can reach your customers anywhere and we research to find out exactly what they want."
	},
    "cards":[
        
        {
            "id":1,
            "title":"Blog Posts",
            "image":"illo-BlogPosts.svg"
           
        },
        {
            "id":2,
            "title":"Infographics",
            "image":"illo-Infographics.svg"
            
        },
        {
            "id":3,
             "title":"Checklists",
            "image":"illo-Checklists.svg"
            
        },
        {
            "id":4,
             "title":"eBooks",
            "image":"illo-eBooks.svg"
           
        },
        {
            "id":5,
             "title":"Whitepapers",
            "image":"illo-WhitePapers.svg"
        
        },
        {
            "id":6,
             "title":"Case Studies",
            "image":"illo-CaseStudies.svg"
           
        },
        {
            "id":7,
             "title":"Reviews",
            "image":"illo-Reviews.svg"
           
        },
        {
            "id":8,
             "title":"How-to Guides",
            "image":"illo-HowToGuides.svg"
           
        },
        {
            "id":9,
             "title":"Guest Posts",
            "image":"illo-GuestPosts.svg"
        }
    ]

}